{
  "updated": "2026-07-17T05:00:54.484Z",
  "players": [
    {
      "username": "6LR",
      "totalLevel": 1167,
      "totalXp": 18485813,
      "stats": {
        "Overall": {
          "rank": -1,
          "level": 1167,
          "xp": 18485813
        },
        "Attack": {
          "rank": -1,
          "level": 46,
          "xp": 70464
        },
        "Defence": {
          "rank": -1,
          "level": 50,
          "xp": 110374
        },
        "Strength": {
          "rank": -1,
          "level": 41,
          "xp": 44533
        },
        "Hitpoints": {
          "rank": -1,
          "level": 66,
          "xp": 540823
        },
        "Ranged": {
          "rank": 1866164,
          "level": 77,
          "xp": 1495214
        },
        "Prayer": {
          "rank": -1,
          "level": 43,
          "xp": 55180
        },
        "Magic": {
          "rank": -1,
          "level": 53,
          "xp": 141923
        },
        "Cooking": {
          "rank": -1,
          "level": 53,
          "xp": 149033
        },
        "Woodcutting": {
          "rank": -1,
          "level": 52,
          "xp": 131891
        },
        "Fletching": {
          "rank": -1,
          "level": 27,
          "xp": 10674
        },
        "Fishing": {
          "rank": -1,
          "level": 54,
          "xp": 155340
        },
        "Firemaking": {
          "rank": -1,
          "level": 50,
          "xp": 102995
        },
        "Crafting": {
          "rank": -1,
          "level": 46,
          "xp": 74083
        },
        "Smithing": {
          "rank": -1,
          "level": 37,
          "xp": 29195
        },
        "Mining": {
          "rank": -1,
          "level": 50,
          "xp": 109144
        },
        "Herblore": {
          "rank": -1,
          "level": 33,
          "xp": 18302
        },
        "Agility": {
          "rank": 68027,
          "level": 99,
          "xp": 13267567
        },
        "Thieving": {
          "rank": 711745,
          "level": 77,
          "xp": 1510393
        },
        "Slayer": {
          "rank": -1,
          "level": 40,
          "xp": 38013
        },
        "Farming": {
          "rank": 1854352,
          "level": 46,
          "xp": 71861
        },
        "Runecrafting": {
          "rank": -1,
          "level": 27,
          "xp": 10055
        },
        "Hunter": {
          "rank": 1532278,
          "level": 61,
          "xp": 315176
        },
        "Construction": {
          "rank": -1,
          "level": 38,
          "xp": 33580
        },
        "Sailing": {
          "rank": -1,
          "level": 1,
          "xp": 0
        }
      },
      "gains": {},
      "totalGain": 0,
      "activities": {
        "Clue Scrolls (all)": {
          "rank": 930065,
          "score": 37
        },
        "Clue Scrolls (medium)": {
          "rank": 406272,
          "score": 37
        }
      },
      "activityGains": {}
    },
    {
      "username": "Iron Shiifty",
      "totalLevel": 2136,
      "totalXp": 196285536,
      "stats": {
        "Overall": {
          "rank": 291112,
          "level": 2136,
          "xp": 196285536
        },
        "Attack": {
          "rank": 199265,
          "level": 99,
          "xp": 16328087
        },
        "Defence": {
          "rank": 224062,
          "level": 99,
          "xp": 14497941
        },
        "Strength": {
          "rank": 214465,
          "level": 99,
          "xp": 22229101
        },
        "Hitpoints": {
          "rank": 262573,
          "level": 99,
          "xp": 28486918
        },
        "Ranged": {
          "rank": 319731,
          "level": 99,
          "xp": 20955036
        },
        "Prayer": {
          "rank": 350448,
          "level": 90,
          "xp": 5346806
        },
        "Magic": {
          "rank": 454214,
          "level": 99,
          "xp": 13536491
        },
        "Cooking": {
          "rank": 546213,
          "level": 94,
          "xp": 8452234
        },
        "Woodcutting": {
          "rank": 596377,
          "level": 85,
          "xp": 3546139
        },
        "Fletching": {
          "rank": 461314,
          "level": 91,
          "xp": 5958437
        },
        "Fishing": {
          "rank": 417727,
          "level": 89,
          "xp": 5144888
        },
        "Firemaking": {
          "rank": 667408,
          "level": 89,
          "xp": 5271028
        },
        "Crafting": {
          "rank": 321683,
          "level": 93,
          "xp": 7439917
        },
        "Smithing": {
          "rank": 506856,
          "level": 84,
          "xp": 2958645
        },
        "Mining": {
          "rank": 712916,
          "level": 81,
          "xp": 2318610
        },
        "Herblore": {
          "rank": 334860,
          "level": 90,
          "xp": 5356219
        },
        "Agility": {
          "rank": 443425,
          "level": 82,
          "xp": 2421627
        },
        "Thieving": {
          "rank": 532249,
          "level": 82,
          "xp": 2479771
        },
        "Slayer": {
          "rank": 257284,
          "level": 98,
          "xp": 12444645
        },
        "Farming": {
          "rank": 665246,
          "level": 87,
          "xp": 4056882
        },
        "Runecrafting": {
          "rank": 517028,
          "level": 76,
          "xp": 1418272
        },
        "Hunter": {
          "rank": 494792,
          "level": 82,
          "xp": 2487081
        },
        "Construction": {
          "rank": 684598,
          "level": 82,
          "xp": 2566676
        },
        "Sailing": {
          "rank": 310111,
          "level": 67,
          "xp": 584085
        }
      },
      "gains": {},
      "totalGain": 0,
      "activities": {
        "Clue Scrolls (all)": {
          "rank": 116408,
          "score": 629
        },
        "Clue Scrolls (beginner)": {
          "rank": 1184919,
          "score": 3
        },
        "Clue Scrolls (easy)": {
          "rank": 212450,
          "score": 44
        },
        "Clue Scrolls (medium)": {
          "rank": 45386,
          "score": 394
        },
        "Clue Scrolls (hard)": {
          "rank": 179115,
          "score": 161
        },
        "Clue Scrolls (elite)": {
          "rank": 226126,
          "score": 25
        },
        "Clue Scrolls (master)": {
          "rank": 428326,
          "score": 2
        },
        "Abyssal Sire": {
          "rank": 21308,
          "score": 1210
        },
        "Alchemical Hydra": {
          "rank": 140054,
          "score": 571
        },
        "Amoxliatl": {
          "rank": 162951,
          "score": 33
        },
        "Araxxor": {
          "rank": 132147,
          "score": 351
        },
        "Barrows Chests": {
          "rank": 62079,
          "score": 714
        },
        "Brutus": {
          "rank": 47068,
          "score": 1019
        },
        "Callisto": {
          "rank": 319951,
          "score": 6
        },
        "Cal'varion": {
          "rank": 99408,
          "score": 157
        },
        "Cerberus": {
          "rank": 173105,
          "score": 499
        },
        "Chambers of Xeric": {
          "rank": -1,
          "score": 1
        },
        "Chaos Elemental": {
          "rank": -1,
          "score": 3
        },
        "Commander Zilyana": {
          "rank": 255252,
          "score": 32
        },
        "Crazy Archaeologist": {
          "rank": 222856,
          "score": 40
        },
        "Dagannoth Prime": {
          "rank": 443361,
          "score": 15
        },
        "Dagannoth Rex": {
          "rank": 159855,
          "score": 326
        },
        "Dagannoth Supreme": {
          "rank": 429074,
          "score": 18
        },
        "Duke Sucellus": {
          "rank": 102051,
          "score": 213
        },
        "General Graardor": {
          "rank": 387496,
          "score": 42
        },
        "Giant Mole": {
          "rank": 540543,
          "score": 20
        },
        "Grotesque Guardians": {
          "rank": 138896,
          "score": 190
        },
        "Hespori": {
          "rank": 551038,
          "score": 20
        },
        "Kalphite Queen": {
          "rank": 292100,
          "score": 23
        },
        "King Black Dragon": {
          "rank": 529227,
          "score": 37
        },
        "Kraken": {
          "rank": 233010,
          "score": 1371
        },
        "K'ril Tsutsaroth": {
          "rank": 52224,
          "score": 324
        },
        "Lunar Chests": {
          "rank": 653,
          "score": 833
        },
        "Mimic": {
          "rank": 289177,
          "score": 1
        },
        "Nex": {
          "rank": 34463,
          "score": 45
        },
        "Phantom Muspah": {
          "rank": -1,
          "score": 4
        },
        "Sarachnis": {
          "rank": 270841,
          "score": 45
        },
        "Skotizo": {
          "rank": 533259,
          "score": 9
        },
        "Tempoross": {
          "rank": 1140926,
          "score": 5
        },
        "The Gauntlet": {
          "rank": 177524,
          "score": 23
        },
        "The Corrupted Gauntlet": {
          "rank": 121376,
          "score": 300
        },
        "The Hueycoatl": {
          "rank": 36582,
          "score": 216
        },
        "The Leviathan": {
          "rank": -1,
          "score": 1
        },
        "The Royal Titans": {
          "rank": 92998,
          "score": 280
        },
        "The Whisperer": {
          "rank": -1,
          "score": 1
        },
        "Thermonuclear Smoke Devil": {
          "rank": 272801,
          "score": 114
        },
        "Tombs of Amascut": {
          "rank": 340677,
          "score": 7
        },
        "TzTok-Jad": {
          "rank": -1,
          "score": 2
        },
        "Vardorvis": {
          "rank": 162885,
          "score": 20
        },
        "Vorkath": {
          "rank": 440209,
          "score": 135
        },
        "Wintertodt": {
          "rank": 656943,
          "score": 186
        },
        "Yama": {
          "rank": 157936,
          "score": 7
        },
        "Zalcano": {
          "rank": -1,
          "score": 3
        },
        "Zulrah": {
          "rank": 231396,
          "score": 521
        }
      },
      "activityGains": {}
    },
    {
      "username": "5JV",
      "totalLevel": 2023,
      "totalXp": 108711044,
      "stats": {
        "Overall": {
          "rank": 473127,
          "level": 2023,
          "xp": 108711044
        },
        "Attack": {
          "rank": 742851,
          "level": 91,
          "xp": 6283888
        },
        "Defence": {
          "rank": 353586,
          "level": 99,
          "xp": 13220795
        },
        "Strength": {
          "rank": 566968,
          "level": 99,
          "xp": 13442884
        },
        "Hitpoints": {
          "rank": 579548,
          "level": 99,
          "xp": 16364901
        },
        "Ranged": {
          "rank": 802434,
          "level": 95,
          "xp": 9629518
        },
        "Prayer": {
          "rank": 1127401,
          "level": 73,
          "xp": 1023788
        },
        "Magic": {
          "rank": 924268,
          "level": 93,
          "xp": 7443491
        },
        "Cooking": {
          "rank": 884288,
          "level": 83,
          "xp": 2911571
        },
        "Woodcutting": {
          "rank": 682048,
          "level": 83,
          "xp": 2950112
        },
        "Fletching": {
          "rank": 808103,
          "level": 81,
          "xp": 2220724
        },
        "Fishing": {
          "rank": 1014550,
          "level": 76,
          "xp": 1373804
        },
        "Firemaking": {
          "rank": 831654,
          "level": 85,
          "xp": 3366829
        },
        "Crafting": {
          "rank": 460967,
          "level": 87,
          "xp": 4123355
        },
        "Smithing": {
          "rank": 790924,
          "level": 75,
          "xp": 1336423
        },
        "Mining": {
          "rank": 670267,
          "level": 82,
          "xp": 2521745
        },
        "Herblore": {
          "rank": 758946,
          "level": 76,
          "xp": 1446733
        },
        "Agility": {
          "rank": 534359,
          "level": 80,
          "xp": 2012726
        },
        "Thieving": {
          "rank": 624251,
          "level": 80,
          "xp": 1989849
        },
        "Slayer": {
          "rank": 642310,
          "level": 87,
          "xp": 4245137
        },
        "Farming": {
          "rank": 885975,
          "level": 80,
          "xp": 2093903
        },
        "Runecrafting": {
          "rank": 606897,
          "level": 72,
          "xp": 960030
        },
        "Hunter": {
          "rank": 409067,
          "level": 84,
          "xp": 3049097
        },
        "Construction": {
          "rank": 620235,
          "level": 83,
          "xp": 2708383
        },
        "Sailing": {
          "rank": 220222,
          "level": 80,
          "xp": 1991358
        }
      },
      "gains": {},
      "totalGain": 0,
      "activities": {
        "Clue Scrolls (all)": {
          "rank": 379552,
          "score": 194
        },
        "Clue Scrolls (beginner)": {
          "rank": 1461629,
          "score": 2
        },
        "Clue Scrolls (easy)": {
          "rank": 622916,
          "score": 10
        },
        "Clue Scrolls (medium)": {
          "rank": 158412,
          "score": 129
        },
        "Clue Scrolls (hard)": {
          "rank": 461490,
          "score": 52
        },
        "Clue Scrolls (elite)": {
          "rank": 797231,
          "score": 1
        },
        "Barrows Chests": {
          "rank": 239397,
          "score": 293
        },
        "Cal'varion": {
          "rank": 68847,
          "score": 250
        },
        "Chambers of Xeric": {
          "rank": -1,
          "score": 1
        },
        "Crazy Archaeologist": {
          "rank": 319195,
          "score": 26
        },
        "Dagannoth Prime": {
          "rank": 464918,
          "score": 11
        },
        "Dagannoth Rex": {
          "rank": 282728,
          "score": 182
        },
        "Giant Mole": {
          "rank": 415536,
          "score": 36
        },
        "Grotesque Guardians": {
          "rank": 424672,
          "score": 9
        },
        "Hespori": {
          "rank": 748724,
          "score": 9
        },
        "K'ril Tsutsaroth": {
          "rank": 256003,
          "score": 35
        },
        "Lunar Chests": {
          "rank": 225782,
          "score": 85
        },
        "Phantom Muspah": {
          "rank": -1,
          "score": 1
        },
        "Sarachnis": {
          "rank": 172852,
          "score": 94
        },
        "Spindel": {
          "rank": -1,
          "score": 1
        },
        "Tempoross": {
          "rank": 924138,
          "score": 16
        },
        "The Gauntlet": {
          "rank": 208784,
          "score": 20
        },
        "The Corrupted Gauntlet": {
          "rank": 30818,
          "score": 743
        },
        "The Royal Titans": {
          "rank": 288748,
          "score": 58
        },
        "TzTok-Jad": {
          "rank": -1,
          "score": 1
        },
        "Vorkath": {
          "rank": 710480,
          "score": 31
        },
        "Wintertodt": {
          "rank": 654349,
          "score": 187
        },
        "Zulrah": {
          "rank": -1,
          "score": 1
        }
      },
      "activityGains": {}
    }
  ]
}