{
  "updated": "2026-07-18T20:00:48.316Z",
  "players": [
    {
      "username": "6LR",
      "totalLevel": 1167,
      "totalXp": 18485813,
      "stats": {
        "Overall": {
          "rank": -1,
          "level": 1167,
          "xp": 18485813
        },
        "Attack": {
          "rank": -1,
          "level": 46,
          "xp": 70464
        },
        "Defence": {
          "rank": -1,
          "level": 50,
          "xp": 110374
        },
        "Strength": {
          "rank": -1,
          "level": 41,
          "xp": 44533
        },
        "Hitpoints": {
          "rank": -1,
          "level": 66,
          "xp": 540823
        },
        "Ranged": {
          "rank": 1867006,
          "level": 77,
          "xp": 1495214
        },
        "Prayer": {
          "rank": -1,
          "level": 43,
          "xp": 55180
        },
        "Magic": {
          "rank": -1,
          "level": 53,
          "xp": 141923
        },
        "Cooking": {
          "rank": -1,
          "level": 53,
          "xp": 149033
        },
        "Woodcutting": {
          "rank": -1,
          "level": 52,
          "xp": 131891
        },
        "Fletching": {
          "rank": -1,
          "level": 27,
          "xp": 10674
        },
        "Fishing": {
          "rank": -1,
          "level": 54,
          "xp": 155340
        },
        "Firemaking": {
          "rank": -1,
          "level": 50,
          "xp": 102995
        },
        "Crafting": {
          "rank": -1,
          "level": 46,
          "xp": 74083
        },
        "Smithing": {
          "rank": -1,
          "level": 37,
          "xp": 29195
        },
        "Mining": {
          "rank": -1,
          "level": 50,
          "xp": 109144
        },
        "Herblore": {
          "rank": -1,
          "level": 33,
          "xp": 18302
        },
        "Agility": {
          "rank": 68100,
          "level": 99,
          "xp": 13267567
        },
        "Thieving": {
          "rank": 712216,
          "level": 77,
          "xp": 1510393
        },
        "Slayer": {
          "rank": -1,
          "level": 40,
          "xp": 38013
        },
        "Farming": {
          "rank": 1855187,
          "level": 46,
          "xp": 71861
        },
        "Runecrafting": {
          "rank": -1,
          "level": 27,
          "xp": 10055
        },
        "Hunter": {
          "rank": 1533049,
          "level": 61,
          "xp": 315176
        },
        "Construction": {
          "rank": -1,
          "level": 38,
          "xp": 33580
        },
        "Sailing": {
          "rank": -1,
          "level": 1,
          "xp": 0
        }
      },
      "gains": {},
      "totalGain": 0,
      "activities": {
        "Clue Scrolls (all)": {
          "rank": 930464,
          "score": 37
        },
        "Clue Scrolls (medium)": {
          "rank": 406453,
          "score": 37
        }
      },
      "activityGains": {}
    },
    {
      "username": "Iron Shiifty",
      "totalLevel": 2136,
      "totalXp": 197043132,
      "stats": {
        "Overall": {
          "rank": 291424,
          "level": 2136,
          "xp": 197043132
        },
        "Attack": {
          "rank": 199375,
          "level": 99,
          "xp": 16329073
        },
        "Defence": {
          "rank": 224257,
          "level": 99,
          "xp": 14497941
        },
        "Strength": {
          "rank": 212350,
          "level": 99,
          "xp": 22400906
        },
        "Hitpoints": {
          "rank": 260874,
          "level": 99,
          "xp": 28611362
        },
        "Ranged": {
          "rank": 320018,
          "level": 99,
          "xp": 20955036
        },
        "Prayer": {
          "rank": 350640,
          "level": 90,
          "xp": 5346806
        },
        "Magic": {
          "rank": 437998,
          "level": 99,
          "xp": 13694387
        },
        "Cooking": {
          "rank": 543237,
          "level": 94,
          "xp": 8628279
        },
        "Woodcutting": {
          "rank": 596885,
          "level": 85,
          "xp": 3546139
        },
        "Fletching": {
          "rank": 461572,
          "level": 91,
          "xp": 5958437
        },
        "Fishing": {
          "rank": 413902,
          "level": 89,
          "xp": 5268843
        },
        "Firemaking": {
          "rank": 667798,
          "level": 89,
          "xp": 5271028
        },
        "Crafting": {
          "rank": 321835,
          "level": 93,
          "xp": 7439917
        },
        "Smithing": {
          "rank": 507215,
          "level": 84,
          "xp": 2958645
        },
        "Mining": {
          "rank": 713316,
          "level": 81,
          "xp": 2319295
        },
        "Herblore": {
          "rank": 334473,
          "level": 90,
          "xp": 5357499
        },
        "Agility": {
          "rank": 443393,
          "level": 82,
          "xp": 2421871
        },
        "Thieving": {
          "rank": 532594,
          "level": 82,
          "xp": 2479771
        },
        "Slayer": {
          "rank": 257487,
          "level": 98,
          "xp": 12444645
        },
        "Farming": {
          "rank": 665654,
          "level": 87,
          "xp": 4057138
        },
        "Runecrafting": {
          "rank": 517397,
          "level": 76,
          "xp": 1418272
        },
        "Hunter": {
          "rank": 495142,
          "level": 82,
          "xp": 2487081
        },
        "Construction": {
          "rank": 684998,
          "level": 82,
          "xp": 2566676
        },
        "Sailing": {
          "rank": 310860,
          "level": 67,
          "xp": 584085
        }
      },
      "gains": {},
      "totalGain": 0,
      "activities": {
        "Clue Scrolls (all)": {
          "rank": 116489,
          "score": 629
        },
        "Clue Scrolls (beginner)": {
          "rank": 1185544,
          "score": 3
        },
        "Clue Scrolls (easy)": {
          "rank": 212620,
          "score": 44
        },
        "Clue Scrolls (medium)": {
          "rank": 45423,
          "score": 394
        },
        "Clue Scrolls (hard)": {
          "rank": 179200,
          "score": 161
        },
        "Clue Scrolls (elite)": {
          "rank": 226236,
          "score": 25
        },
        "Clue Scrolls (master)": {
          "rank": 428395,
          "score": 2
        },
        "Abyssal Sire": {
          "rank": 21341,
          "score": 1210
        },
        "Alchemical Hydra": {
          "rank": 140172,
          "score": 571
        },
        "Amoxliatl": {
          "rank": 163264,
          "score": 33
        },
        "Araxxor": {
          "rank": 132365,
          "score": 351
        },
        "Barrows Chests": {
          "rank": 62122,
          "score": 714
        },
        "Brutus": {
          "rank": 47204,
          "score": 1019
        },
        "Callisto": {
          "rank": 320166,
          "score": 6
        },
        "Cal'varion": {
          "rank": 99547,
          "score": 157
        },
        "Cerberus": {
          "rank": 173262,
          "score": 499
        },
        "Chambers of Xeric": {
          "rank": -1,
          "score": 1
        },
        "Chaos Elemental": {
          "rank": -1,
          "score": 3
        },
        "Commander Zilyana": {
          "rank": 255399,
          "score": 32
        },
        "Crazy Archaeologist": {
          "rank": 223007,
          "score": 40
        },
        "Dagannoth Prime": {
          "rank": 443607,
          "score": 15
        },
        "Dagannoth Rex": {
          "rank": 159933,
          "score": 326
        },
        "Dagannoth Supreme": {
          "rank": 429297,
          "score": 18
        },
        "Duke Sucellus": {
          "rank": 90227,
          "score": 269
        },
        "General Graardor": {
          "rank": 387683,
          "score": 42
        },
        "Giant Mole": {
          "rank": 540922,
          "score": 20
        },
        "Grotesque Guardians": {
          "rank": 139028,
          "score": 190
        },
        "Hespori": {
          "rank": 551348,
          "score": 20
        },
        "Kalphite Queen": {
          "rank": 292282,
          "score": 23
        },
        "King Black Dragon": {
          "rank": 529411,
          "score": 37
        },
        "Kraken": {
          "rank": 233113,
          "score": 1371
        },
        "K'ril Tsutsaroth": {
          "rank": 52281,
          "score": 324
        },
        "Lunar Chests": {
          "rank": 658,
          "score": 833
        },
        "Mimic": {
          "rank": 289197,
          "score": 1
        },
        "Nex": {
          "rank": 35200,
          "score": 45
        },
        "Phantom Muspah": {
          "rank": -1,
          "score": 4
        },
        "Sarachnis": {
          "rank": 271191,
          "score": 45
        },
        "Skotizo": {
          "rank": 533525,
          "score": 9
        },
        "Tempoross": {
          "rank": 1141797,
          "score": 5
        },
        "The Gauntlet": {
          "rank": 177626,
          "score": 23
        },
        "The Corrupted Gauntlet": {
          "rank": 121465,
          "score": 300
        },
        "The Hueycoatl": {
          "rank": 36669,
          "score": 216
        },
        "The Leviathan": {
          "rank": -1,
          "score": 1
        },
        "The Royal Titans": {
          "rank": 93232,
          "score": 280
        },
        "The Whisperer": {
          "rank": -1,
          "score": 1
        },
        "Thermonuclear Smoke Devil": {
          "rank": 272951,
          "score": 114
        },
        "Tombs of Amascut": {
          "rank": 340927,
          "score": 7
        },
        "TzTok-Jad": {
          "rank": -1,
          "score": 2
        },
        "Vardorvis": {
          "rank": 163108,
          "score": 20
        },
        "Vorkath": {
          "rank": 440479,
          "score": 135
        },
        "Wintertodt": {
          "rank": 657244,
          "score": 186
        },
        "Yama": {
          "rank": 149075,
          "score": 14
        },
        "Zalcano": {
          "rank": -1,
          "score": 3
        },
        "Zulrah": {
          "rank": 231535,
          "score": 521
        }
      },
      "activityGains": {}
    },
    {
      "username": "5JV",
      "totalLevel": 2024,
      "totalXp": 108817501,
      "stats": {
        "Overall": {
          "rank": 471811,
          "level": 2024,
          "xp": 108817501
        },
        "Attack": {
          "rank": 743381,
          "level": 91,
          "xp": 6283888
        },
        "Defence": {
          "rank": 353420,
          "level": 99,
          "xp": 13222995
        },
        "Strength": {
          "rank": 567453,
          "level": 99,
          "xp": 13442884
        },
        "Hitpoints": {
          "rank": 578940,
          "level": 99,
          "xp": 16394722
        },
        "Ranged": {
          "rank": 801507,
          "level": 95,
          "xp": 9665287
        },
        "Prayer": {
          "rank": 1127995,
          "level": 73,
          "xp": 1023788
        },
        "Magic": {
          "rank": 923298,
          "level": 93,
          "xp": 7469288
        },
        "Cooking": {
          "rank": 884299,
          "level": 83,
          "xp": 2916311
        },
        "Woodcutting": {
          "rank": 682491,
          "level": 83,
          "xp": 2950502
        },
        "Fletching": {
          "rank": 808539,
          "level": 81,
          "xp": 2220724
        },
        "Fishing": {
          "rank": 1013557,
          "level": 76,
          "xp": 1376884
        },
        "Firemaking": {
          "rank": 832076,
          "level": 85,
          "xp": 3366829
        },
        "Crafting": {
          "rank": 461121,
          "level": 87,
          "xp": 4125330
        },
        "Smithing": {
          "rank": 789398,
          "level": 76,
          "xp": 1338398
        },
        "Mining": {
          "rank": 670696,
          "level": 82,
          "xp": 2522135
        },
        "Herblore": {
          "rank": 759373,
          "level": 76,
          "xp": 1446993
        },
        "Agility": {
          "rank": 534680,
          "level": 80,
          "xp": 2012726
        },
        "Thieving": {
          "rank": 624632,
          "level": 80,
          "xp": 1989849
        },
        "Slayer": {
          "rank": 642706,
          "level": 87,
          "xp": 4245137
        },
        "Farming": {
          "rank": 886449,
          "level": 80,
          "xp": 2093963
        },
        "Runecrafting": {
          "rank": 607291,
          "level": 72,
          "xp": 960030
        },
        "Hunter": {
          "rank": 409380,
          "level": 84,
          "xp": 3049097
        },
        "Construction": {
          "rank": 620627,
          "level": 83,
          "xp": 2708383
        },
        "Sailing": {
          "rank": 220748,
          "level": 80,
          "xp": 1991358
        }
      },
      "gains": {},
      "totalGain": 0,
      "activities": {
        "Clue Scrolls (all)": {
          "rank": 379739,
          "score": 194
        },
        "Clue Scrolls (beginner)": {
          "rank": 1462309,
          "score": 2
        },
        "Clue Scrolls (easy)": {
          "rank": 623212,
          "score": 10
        },
        "Clue Scrolls (medium)": {
          "rank": 158495,
          "score": 129
        },
        "Clue Scrolls (hard)": {
          "rank": 461682,
          "score": 52
        },
        "Clue Scrolls (elite)": {
          "rank": 797551,
          "score": 1
        },
        "Barrows Chests": {
          "rank": 239539,
          "score": 293
        },
        "Cal'varion": {
          "rank": 68965,
          "score": 250
        },
        "Chambers of Xeric": {
          "rank": -1,
          "score": 1
        },
        "Crazy Archaeologist": {
          "rank": 319404,
          "score": 26
        },
        "Dagannoth Prime": {
          "rank": 465176,
          "score": 11
        },
        "Dagannoth Rex": {
          "rank": 282910,
          "score": 182
        },
        "Giant Mole": {
          "rank": 415857,
          "score": 36
        },
        "Grotesque Guardians": {
          "rank": 424996,
          "score": 9
        },
        "Hespori": {
          "rank": 749118,
          "score": 9
        },
        "K'ril Tsutsaroth": {
          "rank": 256167,
          "score": 35
        },
        "Lunar Chests": {
          "rank": 226195,
          "score": 85
        },
        "Phantom Muspah": {
          "rank": -1,
          "score": 1
        },
        "Sarachnis": {
          "rank": 173129,
          "score": 94
        },
        "Spindel": {
          "rank": -1,
          "score": 1
        },
        "Tempoross": {
          "rank": 924865,
          "score": 16
        },
        "The Gauntlet": {
          "rank": 208898,
          "score": 20
        },
        "The Corrupted Gauntlet": {
          "rank": 30085,
          "score": 753
        },
        "The Royal Titans": {
          "rank": 289268,
          "score": 58
        },
        "TzTok-Jad": {
          "rank": -1,
          "score": 1
        },
        "Vorkath": {
          "rank": 710912,
          "score": 31
        },
        "Wintertodt": {
          "rank": 654646,
          "score": 187
        },
        "Zulrah": {
          "rank": -1,
          "score": 1
        }
      },
      "activityGains": {}
    }
  ]
}